[{
  "_id": {
    "$oid": "61c1b4bc5351d79ba9306459"
  },
  "mark": 175,
  "rank": 1
},{
  "_id": {
    "$oid": "61c1b8345351d79ba930645a"
  },
  "mark": 174,
  "rank": 2
},{
  "_id": {
    "$oid": "61c1b8535351d79ba930645b"
  },
  "mark": 173,
  "rank": 3
},{
  "_id": {
    "$oid": "61c1b8645351d79ba930645c"
  },
  "mark": 172,
  "rank": 4
},{
  "_id": {
    "$oid": "61c1b87c5351d79ba930645d"
  },
  "mark": 171,
  "rank": 5
},{
  "_id": {
    "$oid": "61c1b8825351d79ba930645e"
  },
  "mark": 170,
  "rank": 6
},{
  "_id": {
    "$oid": "61c1b8895351d79ba930645f"
  },
  "mark": 169,
  "rank": 7
},{
  "_id": {
    "$oid": "61c1b8905351d79ba9306460"
  },
  "mark": 168,
  "rank": 8
},{
  "_id": {
    "$oid": "61c1b8af5351d79ba9306461"
  },
  "mark": 167.5,
  "rank": 9
},{
  "_id": {
    "$oid": "61c1b8be5351d79ba9306462"
  },
  "mark": 167,
  "rank": 15
},{
  "_id": {
    "$oid": "61c1b8cd5351d79ba9306463"
  },
  "mark": 165,
  "rank": 25
},{
  "_id": {
    "$oid": "61c1b8ed5351d79ba9306464"
  },
  "mark": 162.5,
  "rank": 35
},{
  "_id": {
    "$oid": "61c1b9025351d79ba9306465"
  },
  "mark": 159.5,
  "rank": 45
},{
  "_id": {
    "$oid": "61c1b91f5351d79ba9306466"
  },
  "mark": 158,
  "rank": 55
},{
  "_id": {
    "$oid": "61c1b9315351d79ba9306467"
  },
  "mark": 155,
  "rank": 65
},{
  "_id": {
    "$oid": "61c1b95e5351d79ba9306468"
  },
  "mark": 154,
  "rank": 75
},{
  "_id": {
    "$oid": "61c1b98e5351d79ba9306469"
  },
  "mark": 151,
  "rank": 85
},{
  "_id": {
    "$oid": "61c1b99b5351d79ba930646a"
  },
  "mark": 150,
  "rank": 95
},{
  "_id": {
    "$oid": "61c1b9b15351d79ba930646b"
  },
  "mark": 148,
  "rank": 105
},{
  "_id": {
    "$oid": "61c1b9f85351d79ba930646c"
  },
  "mark": 147,
  "rank": 115
},{
  "_id": {
    "$oid": "61c1ba035351d79ba930646d"
  },
  "mark": 145,
  "rank": 125
},{
  "_id": {
    "$oid": "61c1ba155351d79ba930646e"
  },
  "mark": 144,
  "rank": 135
},{
  "_id": {
    "$oid": "61c1ba295351d79ba930646f"
  },
  "mark": 143,
  "rank": 145
},{
  "_id": {
    "$oid": "61c1ba455351d79ba9306470"
  },
  "mark": 142,
  "rank": 155
},{
  "_id": {
    "$oid": "61c1ba7f5351d79ba9306471"
  },
  "mark": 141.5,
  "rank": 165
},{
  "_id": {
    "$oid": "61c1ba905351d79ba9306472"
  },
  "mark": 140,
  "rank": 175
},{
  "_id": {
    "$oid": "61c1ba9d5351d79ba9306473"
  },
  "mark": 138.5,
  "rank": 185
},{
  "_id": {
    "$oid": "61c1bab15351d79ba9306474"
  },
  "mark": 138,
  "rank": 195
},{
  "_id": {
    "$oid": "61c1babc5351d79ba9306475"
  },
  "mark": 137.5,
  "rank": 205
},{
  "_id": {
    "$oid": "61c1bacf5351d79ba9306476"
  },
  "mark": 137,
  "rank": 215
},{
  "_id": {
    "$oid": "61c1bafe5351d79ba9306477"
  },
  "mark": 136.5,
  "rank": 225
},{
  "_id": {
    "$oid": "61c1bb0a5351d79ba9306478"
  },
  "mark": 136,
  "rank": 235
},{
  "_id": {
    "$oid": "61c1bb165351d79ba9306479"
  },
  "mark": 135,
  "rank": 245
},{
  "_id": {
    "$oid": "61c1bb2c5351d79ba930647a"
  },
  "mark": 134.5,
  "rank": 255
},{
  "_id": {
    "$oid": "61c1bb415351d79ba930647b"
  },
  "mark": 134,
  "rank": 265
},{
  "_id": {
    "$oid": "61c213c15351d79ba930647c"
  },
  "mark": 133.5,
  "rank": 275
},{
  "_id": {
    "$oid": "61c213d45351d79ba930647d"
  },
  "mark": 133,
  "rank": 285
},{
  "_id": {
    "$oid": "61c213ea5351d79ba930647e"
  },
  "mark": 132.5,
  "rank": 295
},{
  "_id": {
    "$oid": "61c213ff5351d79ba930647f"
  },
  "mark": 131.5,
  "rank": 305
},{
  "_id": {
    "$oid": "61c2141f5351d79ba9306480"
  },
  "mark": 130.5,
  "rank": 315
},{
  "_id": {
    "$oid": "61c214305351d79ba9306481"
  },
  "mark": 129.5,
  "rank": 325
},{
  "_id": {
    "$oid": "61c214445351d79ba9306482"
  },
  "mark": 128.5,
  "rank": 335
},{
  "_id": {
    "$oid": "61c214525351d79ba9306483"
  },
  "mark": 127.5,
  "rank": 345
},{
  "_id": {
    "$oid": "61c214665351d79ba9306484"
  },
  "mark": 126.5,
  "rank": 355
},{
  "_id": {
    "$oid": "61c214865351d79ba9306485"
  },
  "mark": 126,
  "rank": 365
},{
  "_id": {
    "$oid": "61c214945351d79ba9306486"
  },
  "mark": 125,
  "rank": 375
},{
  "_id": {
    "$oid": "61c214ae5351d79ba9306487"
  },
  "mark": 124,
  "rank": 385
},{
  "_id": {
    "$oid": "61c214c95351d79ba9306488"
  },
  "mark": 123,
  "rank": 395
},{
  "_id": {
    "$oid": "61c214e45351d79ba9306489"
  },
  "mark": 122,
  "rank": 405
},{
  "_id": {
    "$oid": "61c214fa5351d79ba930648a"
  },
  "mark": 115,
  "rank": 705
},{
  "_id": {
    "$oid": "61c2156a5351d79ba930648c"
  },
  "mark": 110,
  "rank": 1250
},{
  "_id": {
    "$oid": "61c215735351d79ba930648d"
  },
  "mark": 107.5,
  "rank": 1750
},{
  "_id": {
    "$oid": "61c215845351d79ba930648e"
  },
  "mark": 105,
  "rank": 2250
},{
  "_id": {
    "$oid": "61c215985351d79ba930648f"
  },
  "mark": 102.5,
  "rank": 2750
},{
  "_id": {
    "$oid": "61c215a95351d79ba9306490"
  },
  "mark": 97.5,
  "rank": 3250
},{
  "_id": {
    "$oid": "61c217d95351d79ba9306491"
  },
  "mark": 95,
  "rank": 3750
},{
  "_id": {
    "$oid": "61c217e85351d79ba9306492"
  },
  "mark": 87.5,
  "rank": 4250
},{
  "_id": {
    "$oid": "61c217f25351d79ba9306493"
  },
  "mark": 82.5,
  "rank": 4750
},{
  "_id": {
    "$oid": "61c217ff5351d79ba9306494"
  },
  "mark": 77.5,
  "rank": 5250
},{
  "_id": {
    "$oid": "61c218085351d79ba9306495"
  },
  "mark": 72.5,
  "rank": 5750
},{
  "_id": {
    "$oid": "61c2181f5351d79ba9306496"
  },
  "mark": 67.5,
  "rank": 8000
},{
  "_id": {
    "$oid": "61c218645351d79ba9306497"
  },
  "mark": 62.5,
  "rank": 15000
},{
  "_id": {
    "$oid": "61c2187c5351d79ba9306498"
  },
  "mark": 57.5,
  "rank": 30000
},{
  "_id": {
    "$oid": "61c218895351d79ba9306499"
  },
  "mark": 52.5,
  "rank": 45000
},{
  "_id": {
    "$oid": "61c218955351d79ba930649a"
  },
  "mark": 47.5,
  "rank": 55000
}]